smilestats/__init__.py
smilestats/aromatic_ring_count.py
smilestats/cl_count.py
smilestats/helper.py
smilestats/hydroxy_group_count.py
smilestats/methyl_group_count.py
smilestats/methylene_group_count.py
smilestats-0.1.0.dist-info/METADATA
smilestats-0.1.0.dist-info/WHEEL
smilestats-0.1.0.dist-info/top_level.txt
smilestats-0.1.0.dist-info/RECORD
