Metadata-Version: 2.1
Name: smilestats
Version: 0.1.0
Summary: A package to calculate molecule statistics by their smile encoding.
Author-email: Barkov Mikhail <mik.bar@tutamail.com>
Project-URL: Homepage, https://github.com/MikBark/smilestats
Keywords: SMILES,cheminformatics,chemistry
Requires-Dist: pysmiles==1.1.2
Requires-Dist: importlib-metadata; python_version >= "3.8"
